src/__init__.py
src/cli.py
src/version.py
multirepo_manager-1.0.1.dist-info/LICENSE
multirepo_manager-1.0.1.dist-info/METADATA
multirepo_manager-1.0.1.dist-info/WHEEL
multirepo_manager-1.0.1.dist-info/entry_points.txt
multirepo_manager-1.0.1.dist-info/top_level.txt
multirepo_manager-1.0.1.dist-info/RECORD
